peepdb/__init__.py
peepdb/__main__.py
peepdb/cli.py
peepdb/config.py
peepdb/core.py
peepdb/exceptions.py
peepdb/db/__init__.py
peepdb/db/base.py
peepdb/db/mariadb.py
peepdb/db/mongodb.py
peepdb/db/mysql.py
peepdb/db/postgresql.py
peepdb/db/sqlite.py
peepdb/tests/__init__.py
peepdb/tests/test_cli.py
peepdb/tests/test_connection.py
peepdb/tests/test_data_types.py
peepdb/tests/test_peepdb.py
peepdb/tests/test_sqlite.py
peepdb-0.1.4.dist-info/LICENSE
peepdb-0.1.4.dist-info/METADATA
peepdb-0.1.4.dist-info/WHEEL
peepdb-0.1.4.dist-info/entry_points.txt
peepdb-0.1.4.dist-info/top_level.txt
peepdb-0.1.4.dist-info/RECORD
