Metadata-Version: 2.1
Name: peepdb
Version: 0.1.4
Summary: CLI tool to view database tables fast
Home-page: https://github.com/PeepDB-dev/peepdb
Author: Evangelos Meklis
Author-email: vmeklis@hotmail.com
Classifier: Development Status :: 3 - Alpha
Classifier: Intended Audience :: Developers
Classifier: License :: OSI Approved :: MIT License
Classifier: Operating System :: OS Independent
Classifier: Programming Language :: Python :: 3
Classifier: Programming Language :: Python :: 3.9
Classifier: Programming Language :: Python :: 3.10
Classifier: Programming Language :: Python :: 3.11
Requires-Python: >=3.9
License-File: LICENSE
Requires-Dist: mysql-connector-python >=9.0.0
Requires-Dist: psycopg2-binary >=2.9.9
Requires-Dist: pymysql >=1.1.1
Requires-Dist: cryptography >=43.0.0
Requires-Dist: tabulate >=0.8.9
Requires-Dist: click >=8.0.0
Requires-Dist: mariadb
Requires-Dist: cachetools >=5.5.0
Requires-Dist: keyring >=25.4.1
Requires-Dist: pymongo ==4.9.1
Requires-Dist: dnspython ==2.6.1
Provides-Extra: dev
Requires-Dist: coverage >=7.6.1 ; extra == 'dev'
Requires-Dist: pytest >=8.3.2 ; extra == 'dev'
Requires-Dist: pytest-cov >=5.0.0 ; extra == 'dev'
Provides-Extra: system
Requires-Dist: libmariadb3 ; extra == 'system'
Requires-Dist: libmariadb-dev ; extra == 'system'
